LyScriptUtils/__init__.py
LyScriptUtils-1.0.1.dist-info/LICENSE
LyScriptUtils-1.0.1.dist-info/METADATA
LyScriptUtils-1.0.1.dist-info/WHEEL
LyScriptUtils-1.0.1.dist-info/top_level.txt
LyScriptUtils-1.0.1.dist-info/RECORD
